i3_agenda/__init__.py
i3_agenda/api.py
i3_agenda/cache_utils.py
i3_agenda/config.py
i3_agenda/conftest.py
i3_agenda/const.py
i3_agenda/event.py
i3_agenda/helpers.py
i3_agenda/main.py
i3_agenda-1.8.dist-info/LICENSE.txt
i3_agenda-1.8.dist-info/METADATA
i3_agenda-1.8.dist-info/WHEEL
i3_agenda-1.8.dist-info/entry_points.txt
i3_agenda-1.8.dist-info/top_level.txt
i3_agenda-1.8.dist-info/RECORD
