Metadata-Version: 2.1
Name: i3-agenda
Version: 1.8
Summary: Show your next google calendar event in polybar or i3-bar
Author-email: Tomer Rosenfeld <mail@tomerrosenfeld.com>
License: Unlicense
Project-URL: Download, https://github.com/rosenpin/i3-agenda/archive/1.8.tar.gz
Classifier: Programming Language :: Python :: 3
Requires-Python: >=3.3
License-File: LICENSE.txt
Requires-Dist: aiohttp
Requires-Dist: google-api-python-client
Requires-Dist: google-auth-httplib2
Requires-Dist: google-auth-oauthlib
Requires-Dist: python-bidi
Requires-Dist: typing-extensions
